src/AWS_utils.py
src/__init__.py
src/entrypoint.py
src/instance_connect.py
aws_devops_cli-0.0.3.dist-info/METADATA
aws_devops_cli-0.0.3.dist-info/WHEEL
aws_devops_cli-0.0.3.dist-info/entry_points.txt
aws_devops_cli-0.0.3.dist-info/top_level.txt
aws_devops_cli-0.0.3.dist-info/RECORD
