Metadata-Version: 2.1
Name: aws-devops-cli
Version: 0.0.3
Requires-Dist: typer
Requires-Dist: boto3
Requires-Dist: inquirer
